{
  "source_url": "https://www.gutenberg.org/ebooks/3479.txt.utf-8",
  "source_page_url": "https://www.gutenberg.org/ebooks/3479",
  "retrieved_at_utc": "2026-05-13T10:06:14.747777+00:00",
  "raw_sha256": "b7946bd40d839b2860f97f0ea7372c91e431ae82cd123952f0b9b4d19758cfc1",
  "clean_sha256": "27f412406c10532f1c9ddd7acaee10172c26f138b6313d57b40d6363517cdf5a",
  "gutenberg_ebook_id": "3479",
  "canonical_title": "The Metal Monster",
  "author": "Abraham Merritt",
  "raw_bytes": 499777,
  "clean_bytes": 480329
}